humiocli/__init__.py
humiocli/cli.py
humiocli/prettyxml.py
humiocli/utils.py
humiocli-0.9.0.dist-info/entry_points.txt
humiocli-0.9.0.dist-info/LICENSE
humiocli-0.9.0.dist-info/WHEEL
humiocli-0.9.0.dist-info/METADATA
humiocli-0.9.0.dist-info/RECORD
