Metadata-Version: 2.1
Name: humiocli
Version: 0.9.0
Summary: Command line interface for interacting with the Humio API using the humioapi library
Home-page: https://github.com/gwtwod/humiocli
Author: Jostein Haukeli
Requires-Python: >=3.8
Classifier: Programming Language :: Python :: 3
Classifier: Programming Language :: Python :: 3.10
Classifier: Programming Language :: Python :: 3.8
Classifier: Programming Language :: Python :: 3.9
Requires-Dist: Pygments (>=2.8.0,<3.0.0)
Requires-Dist: chardet (>=4.0.0,<5.0.0)
Requires-Dist: click (>=7.1.2,<8.0.0)
Requires-Dist: colorama (>=0.4.4,<0.5.0)
Requires-Dist: humioapi (>=0.11.0,<0.12.0)
Requires-Dist: ipykernel (>=5.4.3,<6.0.0)
Requires-Dist: pandas (>=1.1.1,<2.0.0)
Requires-Dist: pendulum (>=2.1.2,<3.0.0)
Requires-Dist: pygments (>=2.6.1,<3.0.0)
Requires-Dist: pytz (>=2018.9,<2019.0)
Requires-Dist: snaptime (>=0.2.4,<0.3.0)
Requires-Dist: structlog (>=20.2.0,<21.0.0)
Requires-Dist: tabulate (>=0.8.8,<0.9.0)
Requires-Dist: tzlocal (>=2.1,<3.0)
Project-URL: Repository, https://github.com/gwtwod/humiocli
